cosmoDA/__init__.py
cosmoDA/cosmoDA.py
cosmoDA/data_utils.py
cosmoDA/plot_utils.py
cosmoDA/util.py
cosmoda-0.1.0.dist-info/METADATA
cosmoda-0.1.0.dist-info/WHEEL
cosmoda-0.1.0.dist-info/licenses/LICENSE
cosmoda-0.1.0.dist-info/RECORD
