Metadata-Version: 2.3
Name: cosmoDA
Version: 0.1.0
Summary: Compositional Score Matching Optimization for Differential Abundance Testing
Project-URL: Homepage, https://github.com/bio-datascience/cosmoDA
Project-URL: Issues, https://github.com/bio-datascience/cosmoDA/issues
Author-email: Johannes Ostner <johannes.ostner@online.de>
License: BSD 3-Clause License
Classifier: Development Status :: 4 - Beta
Classifier: Framework :: Jupyter
Classifier: Intended Audience :: Developers
Classifier: Intended Audience :: Science/Research
Classifier: Natural Language :: English
Classifier: Operating System :: OS Independent
Classifier: Programming Language :: Python :: 3
Classifier: Topic :: Scientific/Engineering :: Bio-Informatics
Requires-Python: >=3.9
Requires-Dist: anndata
Requires-Dist: gglasso
Requires-Dist: jupyter
Requires-Dist: matplotlib
Requires-Dist: numpy
Requires-Dist: pandas
Requires-Dist: rpy2
Requires-Dist: scanpy
Requires-Dist: sccoda
Requires-Dist: scikit-learn
Requires-Dist: scipy
Requires-Dist: seaborn
Requires-Dist: statsmodels
Requires-Dist: ternary
Requires-Dist: tqdm
Requires-Dist: xlrd
